prot/__init__.py
prot/__main__.py
prot/__version__.py
prot/bs/__init__.py
prot/bs/bs.py
prot/bs/bsMap.py
prot/bs/bsPro.py
prot/bs/bsSpaz.py
prot/code.py
prot/pip/__init__.py
prot/pip/__main__.py
prot/pip/extra.py
prot/pip/packagesList.py
prot-3.10.5.dist-info/entry_points.txt
prot-3.10.5.dist-info/LICENSE
prot-3.10.5.dist-info/METADATA
prot-3.10.5.dist-info/WHEEL
prot-3.10.5.dist-info/RECORD
