Metadata-Version: 2.1
Name: prot
Version: 3.10.5
Summary: A Simple Tool That Contains Advance Functions.
Home-page: https://github.com/SAPTeamDEV/prot
License: MIT
Keywords: tool,tools,protools,ptools,colorize
Author: Aeliux
Author-email: itsaeliux@gmail.com
Requires-Python: >=3.8.1,<4.0.0
Classifier: Development Status :: 5 - Production/Stable
Classifier: License :: OSI Approved :: MIT License
Classifier: Programming Language :: Python :: 3
Classifier: Programming Language :: Python :: 3.9
Classifier: Programming Language :: Python :: 3.10
Classifier: Programming Language :: Python :: 3.11
Classifier: Programming Language :: Python :: 3.8
Classifier: Topic :: Software Development :: Libraries
Requires-Dist: colorama (>=0.4.6,<0.5.0)
Requires-Dist: docutils (>=0.20.1,<0.21.0)
